vibrant/__init__.py
vibrant/elements.py
vibrant/material_properties.py
vibrant/materials.py
vibrant/math_extensions.py
vibrant/models.py
vibrant/nodes.py
vibrant-0.0.3.dist-info/entry_points.txt
vibrant-0.0.3.dist-info/LICENSE.md
vibrant-0.0.3.dist-info/WHEEL
vibrant-0.0.3.dist-info/METADATA
vibrant-0.0.3.dist-info/RECORD
