Metadata-Version: 2.1
Name: vibrant
Version: 0.0.3
Summary: PyTorch powered Finite Elements
Home-page: https://pypi.org/project/vibrant
License: MIT
Author: German Capuano
Author-email: e@gcapu.com
Requires-Python: >=3.7,<4.0
Classifier: Development Status :: 1 - Planning
Classifier: License :: OSI Approved :: MIT License
Classifier: Natural Language :: English
Classifier: Operating System :: OS Independent
Classifier: Programming Language :: Python
Classifier: Programming Language :: Python :: 3
Classifier: Programming Language :: Python :: 3.7
Classifier: Programming Language :: Python :: 3.8
Classifier: Topic :: Scientific/Engineering
Classifier: Topic :: Scientific/Engineering :: Physics
Requires-Dist: pyvista (>=0.24,<0.25)
Requires-Dist: torch (>=1.2,<2.0)
Project-URL: Documentation, https://gcapu.github.io
Project-URL: Repository, https://github.com/gcapu/vibrant
